elemento_loyalty_processing/__init__.py
elemento_loyalty_processing/client.py
elemento_loyalty_processing/types.py
elemento_loyalty_processing-1.0.15.dist-info/METADATA
elemento_loyalty_processing-1.0.15.dist-info/WHEEL
elemento_loyalty_processing-1.0.15.dist-info/top_level.txt
elemento_loyalty_processing-1.0.15.dist-info/RECORD
