Metadata-Version: 2.4
Name: elemento-loyalty-processing
Version: 1.0.15
Summary: Elemento Loyalty Processing
Requires-Python: >=3.11
Requires-Dist: kaiju-tools<3,>=2.4.12
Requires-Dist: elemento-customers>=1.0.0
Requires-Dist: kaiju-models<2,>=1.0.4
Provides-Extra: server
Requires-Dist: kaiju-db<3,>=2.3.0; extra == "server"
Requires-Dist: kaiju-redis<3,>=2.4.1; extra == "server"
Provides-Extra: dev
Requires-Dist: kaiju-tools[dev]; extra == "dev"
